py_learning_standards/__init__.py
pylearningstandards-0.2.4.dist-info/LICENSE
pylearningstandards-0.2.4.dist-info/WHEEL
pylearningstandards-0.2.4.dist-info/METADATA
pylearningstandards-0.2.4.dist-info/RECORD
