Metadata-Version: 2.1
Name: pylearningstandards
Version: 0.2.4
Summary: 
Author: Daniel Auerbach
Author-email: auerbach@ict.usc.edu
Requires-Python: >=3.8.4,<4.0.0
Classifier: Programming Language :: Python :: 3
Classifier: Programming Language :: Python :: 3.9
Classifier: Programming Language :: Python :: 3.10
Classifier: Programming Language :: Python :: 3.11
Requires-Dist: dataclass-wizard (>=0.22.3,<0.23.0)
Requires-Dist: pyld (>=2.0.4,<3.0.0)
